MANIFEST.in
README.md
requirements.txt
setup.py
MirrorMirror/ActionDialog.py
MirrorMirror/FrameLessWindow.py
MirrorMirror/ImageShowDialog.py
MirrorMirror/MainWindow.py
MirrorMirror/MirrorMirror.py
MirrorMirror/__init__.py
MirrorMirror.egg-info/PKG-INFO
MirrorMirror.egg-info/SOURCES.txt
MirrorMirror.egg-info/dependency_links.txt
MirrorMirror.egg-info/not-zip-safe
MirrorMirror.egg-info/requires.txt
MirrorMirror.egg-info/top_level.txt
MirrorMirror/augmenters/__init__.py
MirrorMirror/augmenters/arithmetic.py
MirrorMirror/augmenters/artistic.py
MirrorMirror/augmenters/blend.py
MirrorMirror/augmenters/blur.py
MirrorMirror/augmenters/child.py
MirrorMirror/augmenters/color.py
MirrorMirror/augmenters/flip.py
MirrorMirror/augmenters/meta.py
MirrorMirror/augmenters/param.py
MirrorMirror/augmenters/pillike.py
MirrorMirror/augmenters/pooling.py
MirrorMirror/augmenters/segmentation.py
MirrorMirror/augmenters/size.py
MirrorMirror/resources/img/datarefresh.png
MirrorMirror/resources/img/icon.png
MirrorMirror/resources/img/refresh.png
MirrorMirror/theme/Button.py
MirrorMirror/theme/ComboBox.py
MirrorMirror/theme/Frame.py
MirrorMirror/theme/List.py
MirrorMirror/theme/ScrollArea.py
MirrorMirror/theme/SpinBox.py
MirrorMirror/theme/Tab.py
MirrorMirror/theme/TextBox.py
MirrorMirror/theme/__init__.py
MirrorMirror/utils/__init__.py
MirrorMirror/utils/layout.py