Metadata-Version: 2.1
Name: MirrorMirror
Version: 0.1.0
Summary: Easy to Image Augment
Home-page: https://github.com/RubanSeven/MirrorMirror
Author: Hejun Zhu
Author-email: zhuhejun2019@gmail.com
License: Apache
Platform: UNKNOWN
Classifier: Environment :: Web Environment
Classifier: Intended Audience :: Developers
Classifier: Operating System :: OS Independent
Classifier: Topic :: Text Processing :: Indexing
Classifier: Topic :: Utilities
Classifier: Topic :: Internet
Classifier: Topic :: Software Development :: Libraries :: Python Modules
Classifier: Programming Language :: Python :: 3.5
Classifier: Programming Language :: Python :: 3.6
